Workbook

Sheet base de produccion
A1: Lacteos Altos de Teusacá SAS
A3: Año base | B3: 2025
A4: Dias operativos | B4: 312 | C4: dias/ año
A5: Acopio | B5: 150000 | C5: L/dia
A6: Precio Leche en puesta en planta | B6: 2400 | C6: COP/L
A7: Leche anual | B7: =B4*B5 -> 46800000 | C7: L
A8: Costo anual de leche | B8: =+B6*B7/1000000 -> 112320 | C8: millones COP
A9: Tasa de impuestos | B9: 35 | C9: %
A10: Gastos financieros | B10: 4500 | C10: millones COP
A11: Depreciacion anual | B11: 7000 | C11: millones COP
A12: Aumeto de capital de trabajo | B12: 4000 | C12: millones COP
A13: CAPEX | B13: 9000 | C13: millones COP
A14: Trabajadores operativos | B14: 180 | C14: Personas
A15: Costo mensual por operativo | B15: 4300000 | C15: COP/persona
A16: Trabajadores administrativos | B16: 50 | C16: Personas
A17: Costo mensual por administrativo | B17: 8100000 | C17: COP/persona
A20: Presupuestos operativos
A21: ingredientes | B21: 26000 | C21: millones COP
A22: Empaques | B22: 33000 | C22: millones COP
A23: Energia, frio, vapor y agua | B23: 15000 | C23: millones COP
A24: Otros Insumos productivos | B24: 9000 | C24: millones COP
A25: Mantenimiento, CCIP, Calidad y Ambiente | B25: 8700 | C25: millones COP
A26: Distribucion refrigerada | B26: 14300 | C26: millones COP
A27: Mercadeo y gestion comercial | B27: 11000 | C27: millones COP
A28: Administracion, seguros, TI y otros | B28: 19000 | C28: millones COP

Sheet Detalle de Lineas
A1: Volumenes y precios por lineas
A2: Lineas de producción | B2: Leche cruda (L/dia) | C2: participacion (%) | D2: Produccion final (L/dia) | E2: ingresos anuales (millones COP) | F2: Participacion (%)
A3: Yogures | B3: 58300 | C3: =(B3)/$B$6 -> 0.38866667 | D3: =B3*0.972 -> 56667.6 | E3: =SUM('Detalle de Lineas'!F10:F12) -> 145331.99 | F3: =(E3)/$E$6 -> 0.51311951
A4: Quesos | B4: 50000 | C4: =(B4)/$B$6 -> 0.33333333 | D4: =B4*0.1 -> 5000 | E4: =SUM('Detalle de Lineas'!F13:F15) -> 45006 | F4: =(E4)/$E$6 -> 0.1589014
A5: Leches pasteurizadas | B5: =150000-B4-B3 -> 41700 | C5: =(B5)/$B$6 -> 0.278 | D5: =B5 -> 41700 | E5: =SUM('Detalle de Lineas'!F16:F18) -> 92894.256 | F5: =(E5)/$E$6 -> 0.32797909
A6: Total | B6: =B5+B4+B3 -> 150000 | C6: =(B6)/$B$6 -> 1 | E6: =SUM(E3:E5) -> 283232.25
A9: Detalle de las lineas | B9: Presentacion | C9: Produccion diaria (kg) | D9: Produccion anual (kg) | E9: Precio unitario (COP) | F9: Precio total (millones COP)
A10: Yogures | B10: Yogur fresa (mix 150 g/1.000 g/1.750 g) | C10: ='Detalle de Lineas'!$D$3*0.5 -> 28333.8 | D10: =C10*'base de produccion'!$B$4 -> 8840145.6 | E10: 8000 | F10: =E10*D10/1000000 -> 70721.165
A11: Yogures | B11: Yogur natural (mix 200 g/1.000 g) | C11: ='Detalle de Lineas'!$D$3*0.4 -> 22667.04 | D11: =C11*'base de produccion'!$B$4 -> 7072116.5 | E11: 6800 | F11: =E11*D11/1000000 -> 48090.392
A12: Yogures | B12: Yogur griego (mix 150 g/500 g) | C12: ='Detalle de Lineas'!$D$3*0.1 -> 5666.76 | D12: =C12*'base de produccion'!$B$4 -> 1768029.1 | E12: 15000 | F12: =E12*D12/1000000 -> 26520.437
A13: Quesos | B13: Mozzarella(Kg) | C13: ='Detalle de Lineas'!$D$4*0.4 -> 2000 | D13: =C13*'base de produccion'!$B$4 -> 624000 | E13: 35000 | F13: =E13*D13/1000000 -> 21840
A14: Quesos | B14: Doble crema(kg) | C14: ='Detalle de Lineas'!$D$4*0.35 -> 1750 | D14: =C14*'base de produccion'!$B$4 -> 546000 | E14: 21000 | F14: =E14*D14/1000000 -> 11466
A15: Quesos | B15: Quesillo(kg) | C15: ='Detalle de Lineas'!$D$4*0.25 -> 1250 | D15: =C15*'base de produccion'!$B$4 -> 390000 | E15: 30000 | F15: =E15*D15/1000000 -> 11700
A16: Leches Pasteurizadas | B16: Leche Entrera (Litro) | C16: =+'Detalle de Lineas'!$D$5*0.5 -> 20850 | D16: =C16*'base de produccion'!$B$4 -> 6505200 | E16: 3800 | F16: =E16*D16/1000000 -> 24719.76
A17: Leches Pasteurizadas | B17: Leche descremada (Litro) | C17: =+'Detalle de Lineas'!$D$5*0.3 -> 12510 | D17: =C17*'base de produccion'!$B$4 -> 3903120 | E17: 6800 | F17: =E17*D17/1000000 -> 26541.216
A18: Leches Pasteurizadas | B18: Leche Saborizada (Litro) | C18: =+'Detalle de Lineas'!$D$5*0.2 -> 8340 | D18: =C18*'base de produccion'!$B$4 -> 2602080 | E18: 16000 | F18: =E18*D18/1000000 -> 41633.28
F19: =SUM(F10:F18) -> 283232.25

Sheet OPEX
A1: Concepto | B1: COP millones/año
A2: Leche cruda | B2: ='base de produccion'!B8 -> 112320
A3: Ingredientes, cultivos y preparados | B3: ='base de produccion'!$B$21 -> 26000
A4: Empaques | B4: ='base de produccion'!$B$22 -> 33000
A5: Energía y servicios | B5: ='base de produccion'!$B$23 -> 15000
A6: Otros insumos productivos | B6: 8000
A7: Nómina operativa | B7: ='base de produccion'!$B$14*'base de produccion'!$B$15*12/1000000 -> 9288
A8: Mantenimiento, CIP, calidad y ambiente | B8: ='base de produccion'!$B$25 -> 8700
A9: Costo de produccion de caja | B9: =SUM(B2:B8) -> 212308
A10: Distribución refrigerada | B10: 14000
A11: Mercadeo y gestión comercial | B11: 9000
A12: Nómina administrativa y comercial | B12: ='base de produccion'!B16*'base de produccion'!B17*12/1000000 -> 4860
A13: Administración, seguros, TI y otros | B13: 17000
A14: Gastos administrativos y comerciales | B14: =SUM(B10:B13) -> 44860
A15: OPEX de caja | B15: =B14+B9 -> 257168

Sheet CAPEX
A1: Concepto | B1: CAPEX ( COP millones)
A2: Bombas, válvulas y proceso | B2: 3500
A3: Refrigeración, vapor y servicios | B3: 2100
A4: Llenado y empaque | B4: 1800
A5: Adecuaciones sanitarias | B5: 1100
A6: Laboratorio y sistemas | B6: 870
A7: Vehículos y logística | B7: 720
A8: Total | B8: =SUM(B2:B7) -> 10090
A11: Grupo de activos | B11: Valor depreciable (millones COP) | C11: Vida útil (años) | D11: Depreciación anual
A12: Equipos de proceso | B12: 35000 | C12: 10 | D12: =B12/C12 -> 3500
A13: Llenado y empaque | B13: 15000 | C13: 10 | D13: =B13/C13 -> 1500
A14: Servicios industriales | B14: 12000 | C14: 12 | D14: =B14/C14 -> 1000
A15: Cadena de frío | B15: 6000 | C15: 10 | D15: =B15/C15 -> 600
A16: Laboratorio, TI y vehículos | B16: 2000 | C16: 5 | D16: =B16/C16 -> 400
A17: Total | B17: =SUM(B12:B16) -> 70000 | D17: =SUM(D12:D16) -> 7000

Sheet Estado gerencial (Linea de Yogu
A1: Concepto | B1: Fresa | C1: Natural | D1: Griego | E1: Yogures totales | H1: Parámetro | I1: Valor inicial
A2: Ventas brutas | B2: =+'Detalle de Lineas'!F10 -> 70721.165 | C2: =+'Detalle de Lineas'!F11 -> 48090.392 | D2: =+'Detalle de Lineas'!F12 -> 26520.437 | E2: =D2+C2+B2 -> 145331.99 | H2: Lotes fresa/semana | I2: 13
A3: Descuentos y devoluciones | B3: =B2*0.06 -> 4243.2699 | C3: =C2*0.05 -> 2404.5196 | D3: =D2*0.06 -> 1591.2262 | E3: =D3+C3+B3 -> 8239.0157 | H3: Lotes natural/semana | I3: 13
A4: Ventas netas | B4: =B2-B3 -> 66477.895 | C4: =C2-C3 -> 45685.872 | D4: =D2-D3 -> 24929.211 | E4: =E2-E3 -> 137092.98 | H4: Lotes griego/semana | I4: 9
A5: Leche | B5: =(('Detalle de Lineas'!$B$3*0.5)*'base de produccion'!$B$6*'base de produccion'!$B$4)/1000000 -> 21827.52 | C5: =(('Detalle de Lineas'!$B$3*0.4)*'base de produccion'!$B$6*'base de produccion'!$B$4)/1000000 -> 17462.016 | D5: =(('Detalle de Lineas'!$B$3*0.1)*'base de produccion'!$B$6*'base de produccion'!$B$4)/1000000 -> 4365.504 | E5: =SUM(B5:D5) -> 43655.04 | H5: Total lotes/semana | I5: =I2+I3+I4 -> 35
A6: Ingredientes | B6: =B2*0.18 -> 12729.81 | C6: =C2*0.08 -> 3847.2314 | D6: =D2*0.1 -> 2652.0437 | E6: =D6+C6+B6 -> 19229.085 | H6: Trabajadores directos fresa | I6: 22
A7: Empaques | B7: =B2*0.14 -> 9900.9631 | C7: =C2*0.13 -> 6251.751 | D7: =D2*0.16 -> 4243.2699 | E7: =D7+C7+B7 -> 20395.984 | H7: Trabajadores directos natural | I7: 21
A8: Mano de obra directa | B8: =I6*'base de produccion'!$B$15*12/1000000 -> 1135.2 | C8: =I7*'base de produccion'!$B$15*12/1000000 -> 1083.6 | D8: =I8*'base de produccion'!$B$15*12/1000000 -> 722.4 | E8: =D8+C8+B8 -> 2941.2 | H8: Trabajadores directos griego | I8: 14
A9: Margen de contribución | B9: =B4-SUM(B5:B8) -> 20884.402 | C9: =C4-SUM(C5:C8) -> 17041.274 | D9: =D4-SUM(D5:D8) -> 12945.993 | E9: =D9+C9+B9 -> 50871.669 | H9: Energía y servicios línea | I9: 5100
A10: Energía y servicios asignados | B10: 2223.9 | C10: 1813.7 | D10: 762.4 | E10: =D10+C10+B10 -> 4800 | H10: Mantenimiento y CIP línea | I10: 2700
A11: Mantenimiento y CIP asignados | B11: =$I$10*I2/$I$5 -> 1002.8571 | C11: =$I$10*I3/$I$5 -> 1002.8571 | D11: =$I$10*I4/$I$5 -> 694.28571 | E11: =D11+C11+B11 -> 2700 | H11: Calidad de línea | I11: 760
A12: Calidad asignada | B12: =I11*$I$2/$I$5 -> 282.28571 | C12: =I11*$I$3/$I$5 -> 282.28571 | D12: =I11*$I$4/$I$5 -> 195.42857 | E12: =D12+C12+B12 -> 760 | H12: Nómina indirecta línea | I12: 1500
A13: Nómina indirecta asignada | B13: =I12*$I$2/$I$5 -> 557.14286 | C13: =I12*$I$3/$I$5 -> 557.14286 | D13: =I12*$I$4/$I$5 -> 385.71429 | E13: =D13+C13+B13 -> 1500 | H13: Distribución sobre ventas netas | I13: 0.075
A14: Distribución | B14: =B4*$I$13 -> 4985.8421 | C14: =C4*$I$13 -> 3426.4404 | D14: =D4*$I$13 -> 1869.6908 | E14: =D14+C14+B14 -> 10281.973 | H14: Depreciación fresa | I14: 1370
A15: EBITDA de la línea antes de gastos corporativos | B15: =B9-SUM(B10:B14) -> 11832.374 | C15: =C9-SUM(C10:C14) -> 9958.848 | D15: =D9-SUM(D10:D14) -> 9038.4737 | E15: =D15+C15+B15 -> 30829.696 | H15: Depreciación natural | I15: 980
A16: margen EBITDA de la linea | B16: =B15/B4 -> 0.17798961 | C16: =C15/C4 -> 0.21798529 | D16: =D15/D4 -> 0.36256558 | E16: =E15/E4 -> 0.22488166 | H16: Depreciación griego | I16: 580
A17: Depreciación asignada | B17: 1260 | C17: 980 | D17: 560 | E17: =D17+C17+B17 -> 2800
A18: Resultado operativo de la línea antes de gastos corporativos | B18: =B15-B17 -> 10572.374 | C18: =C15-C17 -> 8978.848 | D18: =D15-D17 -> 8478.4737 | E18: =D18+C18+B18 -> 28029.696

Sheet Estado Financiero
A1: Estado finandiero (millones COP)
A2: Ingresos netos | B2: ='Detalle de Lineas'!F19 -> 283232.25
A3: Costo productivo de caja | B3: =OPEX!B9 -> 212308
A4: Utilidad bruta antes de depreciación | B4: =B2-B3 -> 70924.25
A5: Total gastos administrativos | B5: =OPEX!B14 -> 44860
A6: EBITDA | B6: =B4-B5 -> 26064.25
A7: Depreciación y amortización | B7: =CAPEX!D17 -> 7000
A8: Utilidad operacional | B8: =B6-B7 -> 19064.25
A9: Gastos financieros | B9: ='base de produccion'!B10 -> 4500
A10: Utilidad antes de impuestos | B10: =B8-B9 -> 14564.25
A11: Impuesto de renta | B11: =B10*0.35 -> 5097.4874
A12: Utilidad neta | B12: =B10-B11 -> 9466.7623
A15: Flujo de caja | D15: Indicadores Financieros
A16: Utilidad neta | B16: =B12 -> 9466.7623 | D16: Margen bruto de caja | E16: =B4/B2 -> 0.25041022
A17: Depreciacion | B17: =B7 -> 7000 | D17: Margen EBITDA | E17: =B6/B2 -> 0.092024301
A18: Aumento de capital de trabajo | B18: ='base de produccion'!B12 -> 4000 | D18: margen operacional | E18: =B8/B2 -> 0.067309601
A19: Flujo operativo | B19: =B16+B17-B18 -> 12466.762 | D19: margen neto | E19: =+B12/B2 -> 0.033424027
A20: CAPEX | B20: =CAPEX!B8 -> 10090 | D20: EBITDA por litro | E20: =B6/('base de produccion'!$B$7/1000000) -> 556.92841
A21: Flujo de caja libre | B21: =B19-B20 -> 2376.7623 | D21: Utilidad por litro | E21: =B16/('base de produccion'!B7/1000000) -> 202.28125
D22: OPEX por litro | E22: =OPEX!B15/('base de produccion'!$B$7/1000000) -> 5495.0427
D23: Flujo libre por litro | E23: =B21/('base de produccion'!$B$7/1000000) -> 50.785519
D24: Flujo libre por ventas | E24: =B21/B2 -> 0.0083915666
D25: Flujo libre EBITDA | E25: =B21/B6 -> 0.091188594

Sheet Propuesta de mejora
B3: Costo del proyecto | C3: 4340 | D3: MCOP | G3: Vpn
B4: Depreciacion a 10 años | C4: =C3/10 -> 434 | D4: MCOP/año
B5: Capacidad actual | C5: ='Detalle de Lineas'!B3 -> 58300 | D5: L/día
B6: Capacidad meta | C6: 80000 | D6: L/día
B7: Precio promedio yogurt | C7: =(('Detalle de Lineas'!C10*'Detalle de Lineas'!E10)+('Detalle de Lineas'!C11*'Detalle de Lineas'!E11)+('Detalle de Lineas'!C12*'Detalle de Lineas'!E12))/'Detalle de Lineas'!D3 -> 8220 | D7: COP/L
B8: incremento en litros de leche | C8: =C6-C5 -> 21700 | D8: L/día
B9: incremento pocentual | C9: =C8/C5 -> 0.37221269
B10: Tratamiento adicional de leche | C10: =C8*'base de produccion'!B4 -> 6770400 | D10: L/año
B11: Produccion promedio de yogurt | C11: =C10*0.972 -> 6580828.8 | D11: L/año
B12: Ingresos brutos por yogurt | C12: =C7*C11/1000000 -> 54094.413 | D12: por año
B13: utilidad incremental antes de impuestos | C13: =C38-C4 -> 3733.3177 | D13: MCOP
B14: incremento en impuesto | C14: =C13*0.35 -> 1306.6612 | D14: MCOP
B15: utilidad incremental despues de impuestos | C15: =C13-C14 -> 2426.6565 | D15: MCOP
B16: Flujo de caja incremental | C16: =C15+C4 -> 2860.6565 | D16: MCOP
B19: Costos incrementales por aumento
B20: Concepto | C20: Valor anual (COP millones)
B21: Leche adicional | C21: =C11*'base de produccion'!B6/1000000 -> 15793.989
B22: Ingredientes y cultivos | C22: 8558
B23: Empaques | C23: 12124
B24: Energía, agua y frío | C24: 3566
B25: Distribución y comisiones | C25: 5706
B26: Merma y reproceso | C26: 2140
B27: Costos variables incrementales | C27: =SUM(C21:C26) -> 47887.989
B28: Margen de contribucion incremental | C28: =(C12)-C27 -> 6206.4236 | D28: =C28/(C12) -> 0.11473317
B31: Concepto | C31: COP millones/año
B32: Licencias y soporte SCADA | C32: 180
B33: Calibración de instrumentos | C33: 100
B34: Repuestos y mantenimiento especializado | C34: 220
B35: Comunicaciones y ciberseguridad | C35: 80
B36: Capacitación y auditorías | C36: 70
B37: OPEX incremental fijo | C37: 650
B38: EBITDA incremental | C38: =(C28-C37)*0.75 -> 4167.3177
